agentops_core/__init__.py
agentops_core-0.1.0.dist-info/METADATA
agentops_core-0.1.0.dist-info/WHEEL
agentops_core-0.1.0.dist-info/licenses/LICENSE
agentops_core-0.1.0.dist-info/RECORD
